embedlit/__init__.py
embedlit/start.py
embedlit/twitter.py
embedlit-0.0.0.dist-info/LICENSE
embedlit-0.0.0.dist-info/METADATA
embedlit-0.0.0.dist-info/WHEEL
embedlit-0.0.0.dist-info/entry_points.txt
embedlit-0.0.0.dist-info/RECORD
