Metadata-Version: 2.1
Name: embedlit
Version: 0.0.0
Summary: Embed your social media content and other online stuff with ease on Streamlit dashboards
Home-page: https://github.com/ineelhere/embedlit
License: Apache License - Version 2.0
Author: Indraneel Chakraborty
Requires-Python: >=3.8
Classifier: License :: Other/Proprietary License
Classifier: Programming Language :: Python :: 3
Classifier: Programming Language :: Python :: 3.8
Classifier: Programming Language :: Python :: 3.9
Classifier: Programming Language :: Python :: 3.10
Classifier: Programming Language :: Python :: 3.11
Classifier: Programming Language :: Python :: 3.12
Requires-Dist: Streamlit (>=1.15.0)
